{"P2": {"labels": ["\u6d4b\u7ed8"], "postTitle": "\u865a\u62df\u6570\u5b57\u6d4b\u56fe\u7ade\u8d5b\u7ecf\u9a8c\u603b\u7ed3", "postUrl": "post/xu-ni-shu-zi-ce-tu-jing-sai-jing-yan-zong-jie.html", "createdDate": "2024-07-12", "dateLabelColor": "#bc4c00"}, "P1": {"labels": ["\u6742\u8bb0"], "postTitle": "zabwerk\u7684\u6d4b\u8bd5", "postUrl": "post/zabwerk-de-ce-shi.html", "createdDate": "2024-07-10", "dateLabelColor": "#bc4c00"}, "labelColorDict": {"\u6742\u8bb0": "#0075ca", "\u6d4b\u7ed8": "#9B1A07"}}